roman_numbers/__init__.py
roman_numbers/roman.py
roman_numbers-1.0.2.dist-info/LICENSE
roman_numbers-1.0.2.dist-info/METADATA
roman_numbers-1.0.2.dist-info/WHEEL
roman_numbers-1.0.2.dist-info/top_level.txt
roman_numbers-1.0.2.dist-info/RECORD
