Metadata-Version: 2.1
Name: roman-numbers
Version: 1.0.2
Summary: Convert roman numeral to number and manage roman number object
Home-page: UNKNOWN
Author: Jirakit Jirapongwanich
Author-email: jirakit.jpwn@gmail.com
License: UNKNOWN
Platform: UNKNOWN
Classifier: Programming Language :: Python :: 3
Classifier: License :: OSI Approved :: MIT License
Classifier: Operating System :: OS Independent
Requires-Python: >=3.6
